pyline/__init__.py
pyline/pyline.py
pyline-0.3.21.dist-info/AUTHORS.rst
pyline-0.3.21.dist-info/LICENSE
pyline-0.3.21.dist-info/LICENSE.psf
pyline-0.3.21.dist-info/METADATA
pyline-0.3.21.dist-info/WHEEL
pyline-0.3.21.dist-info/entry_points.txt
pyline-0.3.21.dist-info/top_level.txt
pyline-0.3.21.dist-info/RECORD
