Metadata-Version: 2.1
Name: pyline
Version: 0.3.21
Summary: Pyline is a grep-like, sed-like, awk-like command-line tool for line-based text processing in Python.
Home-page: https://github.com/westurner/pyline
Download-URL: https://github.com/westurner/pyline/releases
Author: Wes Turner
Author-email: wes@wrd.nu
License: PSF
Keywords: pyline sed grep
Classifier: Development Status :: 2 - Pre-Alpha
Classifier: Intended Audience :: Developers
Classifier: License :: OSI Approved :: BSD License
Classifier: Natural Language :: English
Classifier: Programming Language :: Python :: 2
Classifier: Programming Language :: Python :: 2.7
Classifier: Programming Language :: Python :: 3
Classifier: Programming Language :: Python :: 3.8
License-File: LICENSE
License-File: LICENSE.psf
License-File: AUTHORS.rst
